quickspacer/__init__.py
quickspacer/constant.py
quickspacer/data.py
quickspacer/model.py
quickspacer/spacer.py
quickspacer/utils.py
quickspacer/resources/vocab.txt
quickspacer/resources/default_saved_model/1/saved_model.pb
quickspacer/resources/default_saved_model/1/assets/vocab.txt
quickspacer/resources/default_saved_model/1/variables/variables.data-00000-of-00001
quickspacer/resources/default_saved_model/1/variables/variables.index
quickspacer/resources/default_saved_model/2/saved_model.pb
quickspacer/resources/default_saved_model/2/assets/vocab.txt
quickspacer/resources/default_saved_model/2/variables/variables.data-00000-of-00001
quickspacer/resources/default_saved_model/2/variables/variables.index
quickspacer/resources/default_saved_model/3/saved_model.pb
quickspacer/resources/default_saved_model/3/assets/vocab.txt
quickspacer/resources/default_saved_model/3/variables/variables.data-00000-of-00001
quickspacer/resources/default_saved_model/3/variables/variables.index
quickspacer-1.0.4.dist-info/METADATA
quickspacer-1.0.4.dist-info/WHEEL
quickspacer-1.0.4.dist-info/top_level.txt
quickspacer-1.0.4.dist-info/RECORD
