Metadata-Version: 2.1
Name: quickspacer
Version: 1.0.4
Summary: Korean spacing correction model that aims for fast speed and moderate accuracy.
Home-page: https://github.com/psj8252/quickspacer.git
Author: Park Sangjun
License: UNKNOWN
Keywords: spacer,korean
Platform: UNKNOWN
Classifier: Development Status :: 4 - Beta
Classifier: Natural Language :: Korean
Classifier: Programming Language :: Python :: 3
Classifier: Topic :: Scientific/Engineering :: Artificial Intelligence
Classifier: Topic :: Text Processing
Requires-Python: >=3.6
Requires-Dist: tensorflow (>=2.0.0)
